poetry_plugin_use_pip_global_index_url/__init__.py
poetry_plugin_use_pip_global_index_url/plugins.py
poetry_plugin_use_pip_global_index_url/py.typed
poetry_plugin_use_pip_global_index_url-0.2.6.dist-info/LICENSE
poetry_plugin_use_pip_global_index_url-0.2.6.dist-info/METADATA
poetry_plugin_use_pip_global_index_url-0.2.6.dist-info/WHEEL
poetry_plugin_use_pip_global_index_url-0.2.6.dist-info/entry_points.txt
poetry_plugin_use_pip_global_index_url-0.2.6.dist-info/RECORD
