Metadata-Version: 2.3
Name: poetry-plugin-use-pip-global-index-url
Version: 0.2.6
Summary: Poetry plugin that sets the global index with the value obtained from pip.
License: BSD-3-Clause
Keywords: packaging,poetry,pypi,pip
Author: Jacob Henner
Author-email: code@ventricle.us
Requires-Python: >=3.9,<4.0
Classifier: License :: OSI Approved :: BSD License
Classifier: Programming Language :: Python :: 3
Classifier: Programming Language :: Python :: 3.9
Classifier: Programming Language :: Python :: 3.10
Classifier: Programming Language :: Python :: 3.11
Classifier: Programming Language :: Python :: 3.12
Classifier: Programming Language :: Python :: 3.13
Requires-Dist: poetry (>=2.0,<2.2)
